clippy/__init__.py
clippy/cli.py
clippy/config.py
clippy/core/explain.py
clippy/core/gen.py
clippy/core/lab.py
clippy/core/note.py
clippy/core/why.py
clippy/utils/ai.py
clippy/utils/fs.py
clippy/utils/parsing.py
clippy/utils/shell.py
clippy_cli-1.0.0.dist-info/licenses/LICENSE
clippy_cli-1.0.0.dist-info/METADATA
clippy_cli-1.0.0.dist-info/WHEEL
clippy_cli-1.0.0.dist-info/entry_points.txt
clippy_cli-1.0.0.dist-info/top_level.txt
clippy_cli-1.0.0.dist-info/RECORD
