Metadata-Version: 2.4
Name: clippy-cli
Version: 1.0.0
Summary: Deterministic-first Linux CLI assistant with optional, gated AI augmentation.
Requires-Python: >=3.8
License-File: LICENSE
Requires-Dist: rich
Requires-Dist: azure-ai-inference
Requires-Dist: python-dotenv
Requires-Dist: azure-core
Dynamic: license-file
